{"mc":{
	"flame1":{
		"frameRate":10,
		"events":[
			
			],
		"frames":[
			
			{
			"res":"61D4136E",
			"x":-78,
			"y":-81
			},
			{
			"res":"AD1A8DCC",
			"x":-76,
			"y":-63
			},
			{
			"res":"BE6EB9FA",
			"x":-73,
			"y":-75
			},
			{
			"res":"84BC16B",
			"x":-75,
			"y":-76
			},
			{
			"res":"601C21E2",
			"x":-70,
			"y":-69
			},
			{
			"res":"FA257DF8",
			"x":-69,
			"y":-70
			},
			{
			"res":"E905C3A3",
			"x":-68,
			"y":-70
			},
			{
			"res":"AE24C6A1",
			"x":-71,
			"y":-63
			},
			{
			"res":"21351CED",
			"x":-70,
			"y":-72
			},
			{
			"res":"6B409513",
			"x":-70,
			"y":-73
			},
			{
			"res":"5920ED1D",
			"x":-74,
			"y":-78
			},
			{
			"res":"FBB0512D",
			"x":-76,
			"y":-88
			},
			{
			"res":"4711D9AB",
			"x":-81,
			"y":-84
			},
			{
			"res":"A7A59E6F",
			"x":-85,
			"y":-90
			},
			{
			"res":"E540D7CE",
			"x":-81,
			"y":-90
			},
			{
			"res":"24D06CC9",
			"x":-72,
			"y":-82
			},
			{
			"res":"4201ED61",
			"x":-68,
			"y":-88
			},
			{
			"res":"C87E286D",
			"x":-71,
			"y":-92
			}
			]
},"flame2":{
		"frameRate":10,
		"events":[
			
			],
		"frames":[
			
			{
			"res":"17E82864",
			"x":-63,
			"y":-65
			},
			{
			"res":"4196F4E0",
			"x":-63,
			"y":-65
			},
			{
			"res":"5FE4C88D",
			"x":-74,
			"y":-78
			},
			{
			"res":"FFEADB1B",
			"x":-95,
			"y":-79
			},
			{
			"res":"34288C5A",
			"x":-91,
			"y":-71
			},
			{
			"res":"648B9413",
			"x":-72,
			"y":-73
			},
			{
			"res":"C7542B83",
			"x":-71,
			"y":-73
			},
			{
			"res":"7D0A28DC",
			"x":-75,
			"y":-70
			},
			{
			"res":"F58AC0A3",
			"x":-75,
			"y":-75
			},
			{
			"res":"63787E5D",
			"x":-75,
			"y":-79
			},
			{
			"res":"67093192",
			"x":-72,
			"y":-86
			},
			{
			"res":"D9532789",
			"x":-78,
			"y":-93
			},
			{
			"res":"9A49240F",
			"x":-85,
			"y":-94
			},
			{
			"res":"14AC1575",
			"x":-90,
			"y":-94
			},
			{
			"res":"295EC6B6",
			"x":-86,
			"y":-94
			},
			{
			"res":"9CDC8BA",
			"x":-84,
			"y":-78
			},
			{
			"res":"DEB6F6A5",
			"x":-67,
			"y":-83
			}
			]
},"flame3":{
		"frameRate":10,
		"events":[
			
			],
		"frames":[
			
			{
			"res":"F5435E1B",
			"x":-78,
			"y":-81
			},
			{
			"res":"8C3B7B02",
			"x":-77,
			"y":-63
			},
			{
			"res":"6FD41CE2",
			"x":-73,
			"y":-86
			},
			{
			"res":"69416359",
			"x":-69,
			"y":-89
			},
			{
			"res":"712450F6",
			"x":-71,
			"y":-81
			},
			{
			"res":"99CC0793",
			"x":-69,
			"y":-70
			},
			{
			"res":"9001EFF9",
			"x":-68,
			"y":-70
			},
			{
			"res":"114DAF8F",
			"x":-71,
			"y":-63
			},
			{
			"res":"82473261",
			"x":-71,
			"y":-72
			},
			{
			"res":"4B1D5467",
			"x":-71,
			"y":-77
			},
			{
			"res":"EB5907B4",
			"x":-69,
			"y":-83
			},
			{
			"res":"7FC7DB9A",
			"x":-74,
			"y":-90
			},
			{
			"res":"933E48F9",
			"x":-82,
			"y":-93
			},
			{
			"res":"47920645",
			"x":-86,
			"y":-92
			},
			{
			"res":"38034D5B",
			"x":-82,
			"y":-93
			},
			{
			"res":"9E0FAA4B",
			"x":-80,
			"y":-75
			},
			{
			"res":"9A109F70",
			"x":-64,
			"y":-80
			},
			{
			"res":"413A872D",
			"x":-56,
			"y":-74
			}
			]
},"flame4":{
		"frameRate":10,
		"events":[
			
			],
		"frames":[
			
			{
			"res":"1D688F14",
			"x":-63,
			"y":-66
			},
			{
			"res":"4B22B330",
			"x":-63,
			"y":-66
			},
			{
			"res":"C267CD1F",
			"x":-71,
			"y":-78
			},
			{
			"res":"D6150C67",
			"x":-72,
			"y":-80
			},
			{
			"res":"D2BDF6E3",
			"x":-74,
			"y":-72
			},
			{
			"res":"D39ABAF4",
			"x":-72,
			"y":-73
			},
			{
			"res":"13B58ED4",
			"x":-71,
			"y":-73
			},
			{
			"res":"91A0F56A",
			"x":-74,
			"y":-66
			},
			{
			"res":"BE14FC2E",
			"x":-74,
			"y":-75
			},
			{
			"res":"C8D5BF88",
			"x":-74,
			"y":-76
			},
			{
			"res":"60A0A6C7",
			"x":-77,
			"y":-81
			},
			{
			"res":"194DD4AD",
			"x":-80,
			"y":-92
			},
			{
			"res":"547DEBED",
			"x":-84,
			"y":-88
			},
			{
			"res":"E10E3053",
			"x":-89,
			"y":-93
			},
			{
			"res":"F9EDE0D1",
			"x":-91,
			"y":-96
			},
			{
			"res":"B2274139",
			"x":-76,
			"y":-85
			},
			{
			"res":"3D3C4DF0",
			"x":-71,
			"y":-92
			},
			{
			"res":"7C273897",
			"x":-74,
			"y":-96
			}
			]
}},
	"res":{
		"47920645":{"x":0,"y":791,"w":187,"h":194},
		"82473261":{"x":725,"y":574,"w":172,"h":174},
		"69416359":{"x":0,"y":1751,"w":170,"h":191},
		"67093192":{"x":172,"y":1751,"w":172,"h":188},
		"5920ED1D":{"x":743,"y":195,"w":174,"h":179},
		"E540D7CE":{"x":0,"y":987,"w":181,"h":191},
		"5FE4C88D":{"x":706,"y":392,"w":174,"h":180},
		"A7A59E6F":{"x":377,"y":396,"w":185,"h":191},
		"91A0F56A":{"x":1072,"y":538,"w":174,"h":167},
		"13B58ED4":{"x":899,"y":553,"w":171,"h":174},
		"63787E5D":{"x":355,"y":1169,"w":175,"h":181},
		"114DAF8F":{"x":520,"y":1728,"w":172,"h":165},
		"F5435E1B":{"x":183,"y":1371,"w":160,"h":162},
		"6B409513":{"x":1055,"y":362,"w":170,"h":174},
		"D2BDF6E3":{"x":532,"y":1151,"w":174,"h":173},
		"24D06CC9":{"x":369,"y":966,"w":172,"h":183},
		"933E48F9":{"x":192,"y":199,"w":183,"h":195},
		"C267CD1F":{"x":390,"y":0,"w":171,"h":179},
		"84BC16B":{"x":706,"y":776,"w":169,"h":178},
		"BE14FC2E":{"x":355,"y":1550,"w":174,"h":176},
		"601C21E2":{"x":1227,"y":354,"w":170,"h":170},
		"EB5907B4":{"x":553,"y":589,"w":170,"h":185},
		"7FC7DB9A":{"x":0,"y":1180,"w":175,"h":192},
		"7D0A28DC":{"x":878,"y":966,"w":175,"h":172},
		"C87E286D":{"x":743,"y":376,"w":77,"h":14},
		"9E0FAA4B":{"x":346,"y":1371,"w":181,"h":177},
		"4196F4E0":{"x":745,"y":0,"w":134,"h":133},
		"21351CED":{"x":1096,"y":179,"w":170,"h":173},
		"D6150C67":{"x":882,"y":0,"w":172,"h":181},
		"4B22B330":{"x":382,"y":781,"w":132,"h":131},
		"C7542B83":{"x":882,"y":376,"w":171,"h":175},
		"194DD4AD":{"x":563,"y":0,"w":180,"h":193},
		"9001EFF9":{"x":1051,"y":729,"w":169,"h":172},
		"60A0A6C7":{"x":176,"y":1561,"w":177,"h":182},
		"1D688F14":{"x":694,"y":1695,"w":132,"h":131},
		"4B1D5467":{"x":346,"y":1745,"w":172,"h":179},
		"547DEBED":{"x":377,"y":183,"w":184,"h":189},
		"C8D5BF88":{"x":1056,"y":0,"w":174,"h":177},
		"17E82864":{"x":564,"y":392,"w":134,"h":133},
		"F9EDE0D1":{"x":0,"y":0,"w":191,"h":197},
		"E10E3053":{"x":0,"y":397,"w":189,"h":194},
		"4711D9AB":{"x":0,"y":1374,"w":181,"h":185},
		"D39ABAF4":{"x":877,"y":776,"w":172,"h":174},
		"14AC1575":{"x":0,"y":199,"w":190,"h":196},
		"99CC0793":{"x":1232,"y":0,"w":170,"h":172},
		"6FD41CE2":{"x":0,"y":1561,"w":174,"h":188},
		"9A109F70":{"x":88,"y":1944,"w":84,"h":69},
		"F58AC0A3":{"x":919,"y":183,"w":175,"h":177},
		"B2274139":{"x":375,"y":593,"w":176,"h":186},
		"D9532789":{"x":563,"y":195,"w":178,"h":195},
		"648B9413":{"x":704,"y":966,"w":172,"h":175},
		"3D3C4DF0":{"x":189,"y":966,"w":77,"h":19},
		"AE24C6A1":{"x":531,"y":1530,"w":171,"h":163},
		"AD1A8DCC":{"x":681,"y":1895,"w":157,"h":129},
		"295EC6B6":{"x":0,"y":593,"w":186,"h":196},
		"E905C3A3":{"x":1404,"y":0,"w":168,"h":171},
		"61D4136E":{"x":543,"y":966,"w":159,"h":161},
		"8C3B7B02":{"x":520,"y":1895,"w":159,"h":129},
		"712450F6":{"x":532,"y":781,"w":172,"h":183},
		"9CDC8BA":{"x":183,"y":987,"w":184,"h":180},
		"4201ED61":{"x":268,"y":966,"w":76,"h":18},
		"FBB0512D":{"x":177,"y":1180,"w":176,"h":189},
		"34288C5A":{"x":189,"y":791,"w":191,"h":173},
		"FA257DF8":{"x":1268,"y":174,"w":169,"h":171},
		"BE6EB9FA":{"x":529,"y":1352,"w":173,"h":176},
		"FFEADB1B":{"x":193,"y":0,"w":195,"h":181},
		"413A872D":{"x":745,"y":135,"w":71,"h":51},
		"DEB6F6A5":{"x":0,"y":1944,"w":86,"h":71},
		"9A49240F":{"x":188,"y":593,"w":185,"h":196},
		"38034D5B":{"x":192,"y":396,"w":183,"h":195},
		"7C273897":{"x":355,"y":1728,"w":78,"h":15}
	}}